pyclasher/__init__.py
pyclasher/exceptions.py
pyclasher/exceptions.pyi
pyclasher/api/__init__.py
pyclasher/api/bulk_requests/__init__.py
pyclasher/api/bulk_requests/abc.py
pyclasher/api/bulk_requests/abc.pyi
pyclasher/api/bulk_requests/b_player.py
pyclasher/api/bulk_requests/b_player.pyi
pyclasher/api/models/__init__.py
pyclasher/api/models/abc.py
pyclasher/api/models/abc.pyi
pyclasher/api/models/base_models.py
pyclasher/api/models/base_models.pyi
pyclasher/api/models/clan.py
pyclasher/api/models/clan.pyi
pyclasher/api/models/clan_builder_base_ranking_list.py
pyclasher/api/models/clan_builder_base_ranking_list.pyi
pyclasher/api/models/clan_capital_raid_seasons.py
pyclasher/api/models/clan_capital_raid_seasons.pyi
pyclasher/api/models/clan_capital_ranking_list.py
pyclasher/api/models/clan_capital_ranking_list.pyi
pyclasher/api/models/clan_list.py
pyclasher/api/models/clan_list.pyi
pyclasher/api/models/clan_member.py
pyclasher/api/models/clan_member.pyi
pyclasher/api/models/clan_member_list.py
pyclasher/api/models/clan_member_list.pyi
pyclasher/api/models/clan_ranking_list.py
pyclasher/api/models/clan_ranking_list.pyi
pyclasher/api/models/clan_war.py
pyclasher/api/models/clan_war.pyi
pyclasher/api/models/clan_war_league_group.py
pyclasher/api/models/clan_war_league_group.pyi
pyclasher/api/models/clan_war_log.py
pyclasher/api/models/clan_war_log.pyi
pyclasher/api/models/enums.py
pyclasher/api/models/enums.pyi
pyclasher/api/models/gold_pass_season.py
pyclasher/api/models/gold_pass_season.pyi
pyclasher/api/models/labels.py
pyclasher/api/models/labels.pyi
pyclasher/api/models/language.py
pyclasher/api/models/language.pyi
pyclasher/api/models/leagues.py
pyclasher/api/models/leagues.pyi
pyclasher/api/models/location.py
pyclasher/api/models/location.pyi
pyclasher/api/models/player.py
pyclasher/api/models/player.pyi
pyclasher/api/models/player_builder_base_ranking_list.py
pyclasher/api/models/player_builder_base_ranking_list.pyi
pyclasher/api/models/player_house.py
pyclasher-1.0.1.dist-info/LICENSE
pyclasher-1.0.1.dist-info/METADATA
pyclasher-1.0.1.dist-info/WHEEL
pyclasher-1.0.1.dist-info/top_level.txt
pyclasher-1.0.1.dist-info/RECORD
