Metadata-Version: 2.1
Name: pyclasher
Version: 1.0.1
Summary: PyClasher - an object-oriented wrapper client for Python that provides easy access to the requested data
Home-page: https://github.com/201st-Luka/PyClasher
Author: 201st-Luka
Author-email: 201stLuka@gmail.com
Keywords: python async clashofclans api wrapper
Classifier: Development Status :: 5 - Production/Stable
Classifier: Framework :: AsyncIO
Classifier: Intended Audience :: Developers
Classifier: License :: OSI Approved :: MIT License
Classifier: Operating System :: OS Independent
Classifier: Programming Language :: Python :: 3.11
Classifier: Programming Language :: Python :: 3.10
Classifier: Topic :: Games/Entertainment
Requires-Python: >=3.10
License-File: LICENSE
Requires-Dist: aiohttp >=3.8
